setup.py
TTMPy/__init__.py
TTMPy.egg-info/PKG-INFO
TTMPy.egg-info/SOURCES.txt
TTMPy.egg-info/dependency_links.txt
TTMPy.egg-info/not-zip-safe
TTMPy.egg-info/top_level.txt