Metadata-Version: 1.0
Name: TTMPy
Version: 0.1
Summary: toolbelt
Home-page: https://github.com/TurkishTinMan/TTMPy
Author: TurkishTinMan
Author-email: riccardo.salladini@gmail.com
License: CC0
Platform: UNKNOWN
